Metadata-Version: 1.1
Name: tddc
Version: 0.1.0
Summary: Scaffold out methods and tests for collaborative data cleaning.
Home-page: https://github.com/DataKind-SG/test-driven-data-cleaning
Author: Oliver Chen
Author-email: oliverxchen@gmail.com
License: MIT
Keywords: data cleaning collaborative
Platform: UNKNOWN
Classifier: Development Status :: 3 - Alpha
Classifier: License :: OSI Approved :: MIT License
Classifier: Programming Language :: Python :: 2.7
Classifier: Programming Language :: Python :: 3.3
Classifier: Programming Language :: Python :: 3.4
Classifier: Programming Language :: Python :: 3.5
